{
  "data": [
    {
      "state": "intro",
      "uuid": "12",
      "fname": "",
      "lname": "",
      "favdoc1": "JOO5T",
      "favdoc2": "BUY",
      "favdoc": "",
      "favcourse1": "CSS",
      "favcourse2": "WAFS",
      "favcourse": "",
      "feedback": "blabla"
    },
    {
      "state": "intro",
      "uuid": "10",
      "fname": "pietje",
      "lname": "snot",
      "anon": "on",
      "favdoc1": "JOO5T",
      "favdoc": "",
      "favcourse2": "WAFS",
      "favcourse": "",
      "feedback": "ok"
    },
    {
      "state": "q4",
      "uuid": "16",
      "fname": "randy",
      "lname": "dd",
      "favdoc1": "JOO5T",
      "favdoc": "",
      "favcourse3": "PWA",
      "favcourse": "",
      "feedback": "fruitje"
    }
  ]
}